unleaky/__init__.py
unleaky/__main__.py
unleaky/unleaky.db
unleaky-0.1.1.dist-info/LICENSE
unleaky-0.1.1.dist-info/METADATA
unleaky-0.1.1.dist-info/WHEEL
unleaky-0.1.1.dist-info/entry_points.txt
unleaky-0.1.1.dist-info/top_level.txt
unleaky-0.1.1.dist-info/RECORD
